demo.py
phootlogger/__init__.py
phootlogger/logger.py
phootlogger-0.1.0.dist-info/licenses/LICENSE
phootlogger-0.1.0.dist-info/METADATA
phootlogger-0.1.0.dist-info/WHEEL
phootlogger-0.1.0.dist-info/top_level.txt
phootlogger-0.1.0.dist-info/RECORD
