Metadata-Version: 2.4
Name: phootlogger
Version: 0.1.0
Summary: Package to print out messages to user.
Author-email: Parker Hooten <parkerhooten@gmail.com>
License: MIT
Project-URL: Homepage, https://github.com/phooten/phootlogger/
Project-URL: Bug Tracker, https://github.com/phooten/phootlogger/issues
Keywords: messages,logger
Classifier: Programming Language :: Python :: 3
Classifier: License :: OSI Approved :: MIT License
Classifier: Operating System :: MacOS
Requires-Python: >=3.7
License-File: LICENSE
Dynamic: license-file
